{"appleSKU":"","appleTeamID":"","enableCodelessAutoInitialization":true,"enableUnityGamingServicesAutoInitialization":false,"products":[{"id":"test1","type":0,"storeIDs":[],"defaultDescription":{"googleLocale":46,"title":"\\ud14c\\uc2a4\\ud2b81","description":"\\ud14c\\uc2a4\\ud2b81 \\uacb0\\uc81c"},"screenshotPath":"","applePriceTier":0,"googlePrice":{"data":[0,0,0,0],"num":0.0},"pricingTemplateID":"","descriptions":[],"payouts":[]},{"id":"test2","type":0,"storeIDs":[],"defaultDescription":{"googleLocale":21,"title":"test2","description":"test2"},"screenshotPath":"","applePriceTier":0,"googlePrice":{"data":[0,0,0,0],"num":0.0},"pricingTemplateID":"","descriptions":[],"payouts":[]},{"id":"","type":0,"storeIDs":[],"defaultDescription":{"googleLocale":21,"title":"","description":""},"screenshotPath":"","applePriceTier":0,"googlePrice":{"data":[0,0,0,0],"num":0.0},"pricingTemplateID":"","descriptions":[],"payouts":[]}]}